setup.cfg
setup.py
conformal/__init__.py
conformal/measures.py
conformal.egg-info/PKG-INFO
conformal.egg-info/SOURCES.txt
conformal.egg-info/dependency_links.txt
conformal.egg-info/not-zip-safe
conformal.egg-info/requires.txt
conformal.egg-info/top_level.txt