Metadata-Version: 1.0
Name: conformal
Version: 0.1
Summary: It is used for conformal prediction
Home-page: UNKNOWN
Author: Anurag Koul
Author-email: koulanurag@gmail.com
License: MIT
Keywords: deep-learning,conformal-prediction,machine-learning
Platform: UNKNOWN
